miniqmt/__init__.py
miniqmt/adapters.py
miniqmt/base.py
miniqmt/core.py
xtquant/__init__.py
xtquant/config/captial_structure_1.ini
xtquant/config/cashflow_new_1.ini
xtquant/config/config.lua
xtquant/config/configHelper.lua
xtquant/config/env.lua
xtquant/config/MarketTime.ini
xtquant/config/metaInfo.json
xtquant/config/pershare_new.ini
xtquant/config/sharebalance_new_1.ini
xtquant/config/shareholder_new_1.ini
xtquant/config/shareincome_new_1.ini
xtquant/config/StockInfo.lua
xtquant/config/table2json.lua
xtquant/config/top10holder_new_1.ini
xtquant/config/tradeTime.txt
xtquant/config/user/root2/lua/config.lua
xtquant/config/user/root2/lua/ConstFunc.lua
xtquant/config/user/root2/lua/FunIndex.lua
xtquant/config/user/root2/lua/FunLogic.lua
xtquant/config/user/root2/lua/FunMath.lua
xtquant/config/user/root2/lua/FunOther.lua
xtquant/config/user/root2/lua/FunRef.lua
xtquant/config/user/root2/lua/FunStatistic.lua
xtquant/config/user/root2/lua/FunString.lua
xtquant/config/user/root2/lua/FunSystem.lua
xtquant/config/user/root2/lua/FunTrader.lua
xtquant/config/user/root2/lua/MetaType.lua
xtquant/config/user/root2/lua/util.lua
xtquant/config/xtquantservice.log4cxx
xtquant/config/xtquantservice.lua
xtquant/config/xtquoterconfig.xml
xtquant/config/xtstocktype.lua
xtquant/datacenter.cp310-win_amd64.pyd
xtquant/datacenter.cp311-win_amd64.pyd
xtquant/datacenter.cp312-win_amd64.pyd
xtquant/datacenter.cp36-win_amd64.pyd
xtquant/datacenter.cp37-win_amd64.pyd
xtquant/datacenter.cp38-win_amd64.pyd
xtquant/datacenter.cp39-win_amd64.pyd
xtquant/doc/xtdata.md
xtquant/doc/xttrader.md
xtquant/libeay32.dll
xtquant/log4cxx.dll
xtquant/metatable/__init__.py
xtquant/msvcp140.dll
xtquant/qmttools/__init__.py
xtquant/qmttools/contextinfo.py
xtquant/qmttools/functions.py
xtquant/qmttools/stgentry.py
xtquant/qmttools/stgframe.py
xtquant/ssleay32.dll
xtquant/vcruntime140.dll
xtquant/xtbson/__init__.py
xtquant/xtbson/bson36/__init__.py
xtquant/xtbson/bson36/_cbson.cp36-win_amd64.pyd
miniqmt-20240829.dist-info/LICENSE
miniqmt-20240829.dist-info/METADATA
miniqmt-20240829.dist-info/WHEEL
miniqmt-20240829.dist-info/RECORD
