Metadata-Version: 2.1
Name: miniqmt
Version: 20240829
Summary: 迅投量化工具的封装包
Home-page: https://gitee.com/vex1023/miniqmt
License: MIT
Keywords: quant,tools,xtquant,miniqmt,xtquant20240329版本
Author: vex1023
Author-email: vex1023@qq.com
Requires-Python: >=3.9,<4.0
Classifier: License :: OSI Approved :: MIT License
Classifier: Programming Language :: Python
Classifier: Programming Language :: Python :: 3
Classifier: Programming Language :: Python :: 3.9
Classifier: Programming Language :: Python :: 3.10
Classifier: Programming Language :: Python :: 3.11
Classifier: Programming Language :: Python :: 3.12
Classifier: Programming Language :: Python :: 3.13
Classifier: Programming Language :: Python :: Implementation :: CPython
Classifier: Programming Language :: Python :: Implementation :: PyPy
Requires-Dist: joblib
Requires-Dist: pydantic (>=2.0,<3.0)
Requires-Dist: python-dateutil
Requires-Dist: requests
Requires-Dist: sqlalchemy (>=1.4,<2.0)
Requires-Dist: vxquant
Requires-Dist: vxutils
